simple_kmeans/__init__.py
simple_kmeans/kmeans.py
simple_kmeans-0.1.2.dist-info/METADATA
simple_kmeans-0.1.2.dist-info/WHEEL
simple_kmeans-0.1.2.dist-info/top_level.txt
simple_kmeans-0.1.2.dist-info/RECORD
