Metadata-Version: 2.1
Name: simple-kmeans
Version: 0.1.2
Summary: Implementation of K-means algorithm from scratch with adaptive distance metrics
Home-page: https://github.com/nullHawk/k-means
Author: Suryansh Shakya
Author-email: suryanshsinghshakya1@gmail.com
Classifier: Programming Language :: Python :: 3
Classifier: License :: OSI Approved :: MIT License
Classifier: Operating System :: OS Independent
Requires-Python: >=3.6
Requires-Dist: numpy
